.gitignore
LICENSE
Makefile
README.md
build.sh
cargo.sh
setup.cfg
setup.py
upload.sh
pandoc_svgbob_filter/__init__.py
pandoc_svgbob_filter.egg-info/PKG-INFO
pandoc_svgbob_filter.egg-info/SOURCES.txt
pandoc_svgbob_filter.egg-info/dependency_links.txt
pandoc_svgbob_filter.egg-info/entry_points.txt
pandoc_svgbob_filter.egg-info/requires.txt
pandoc_svgbob_filter.egg-info/top_level.txt
svgbob/bin/svgbob
svgbob_osx/bin/svgbob
svgbob_win/bin/svgbob.exe
tests/.gitignore
tests/Makefile
tests/data/svgbob.bob
tests/markdown/TITLE.md
tests/markdown/config.yaml