Metadata-Version: 2.1
Name: pandoc-svgbob-filter
Version: 0.0.3
Summary: pandoc filters to render svgbob diagrams
Home-page: https://github.com/pandocker/pandoc-svgbob-filter
Author: pandocker
Author-email: pandocker@github.com
License: UNKNOWN
Project-URL: Source, https://github.com/pandocker/pandoc-svgbob-filter
Keywords: pandoc filter svgbob
Platform: UNKNOWN
Classifier: Development Status :: 3 - Alpha
Classifier: Intended Audience :: Developers
Classifier: Topic :: Software Development :: Build Tools
Classifier: License :: OSI Approved :: MIT License
Classifier: Programming Language :: Python :: 3
Classifier: Programming Language :: Python :: 3.4
Classifier: Programming Language :: Python :: 3.5
Classifier: Programming Language :: Python :: 3.6
Classifier: Programming Language :: Python :: 3.7
